meteor_diceware/__init__.py
meteor_diceware/__main__.py
meteor_diceware/actual_diceware.txt
meteor_diceware/cfg.py
meteor_diceware/default.sqlite3
meteor_diceware/dicecalls.proc.py
meteor_diceware/histograms.py
meteor_diceware/init.sql
meteor_diceware/scraper.py
meteor_diceware/setup.py
meteor_diceware/snowflake.md
meteor_diceware/snowflake.pdf
meteor_diceware/snowflake.py
meteor_diceware/utils.py
meteor_diceware-2.3.0.dist-info/LICENSE
meteor_diceware-2.3.0.dist-info/METADATA
meteor_diceware-2.3.0.dist-info/WHEEL
meteor_diceware-2.3.0.dist-info/top_level.txt
meteor_diceware-2.3.0.dist-info/RECORD
