Metadata-Version: 2.1
Name: meteor-diceware
Version: 2.3.0
Summary: A low-resource, easy to use, low latency, customizable and cryptographically secure implementation of Diceware
Home-page: https://gitlab.com/loggerheads-with-binary/meteor-diceware/
Author: Anna Aniruddh Radhakrishnan
Author-email: dev@aniruddh.ml
License: UNKNOWN
Download-URL: http://pypi.python.org/pypi/meteor-diceware
Project-URL: Documentation, https://gitlab.com/loggerheads-with-binary/meteor-diceware/README.md
Project-URL: Source, https://gitlab.com/loggerheads-with-binary/meteor-diceware/
Project-URL: Tracker, https://gitlab.com/loggerheads-with-binary/meteor-diceware/issues
Platform: UNKNOWN
Classifier: Operating System :: OS Independent
Classifier: Environment :: Console
Classifier: Intended Audience :: Developers
Classifier: Intended Audience :: System Administrators
Classifier: License :: OSI Approved :: MIT License
Classifier: Programming Language :: Python :: 3
Classifier: Natural Language :: English
Classifier: Programming Language :: PL/SQL
Classifier: Topic :: Security :: Cryptography
License-File: LICENSE
Requires-Dist: filehash
Requires-Dist: pretty-traceback
Requires-Dist: coloredlogs
Requires-Dist: colorama
Requires-Dist: termcolor
Requires-Dist: humanize
